setup.py
TtoZ/__init__.py
TtoZ/scripts.py
TtoZ.egg-info/PKG-INFO
TtoZ.egg-info/SOURCES.txt
TtoZ.egg-info/dependency_links.txt
TtoZ.egg-info/entry_points.txt
TtoZ.egg-info/pbr.json
TtoZ.egg-info/requires.txt
TtoZ.egg-info/top_level.txt