Metadata-Version: 1.1
Name: TtoZ
Version: 0.1.2
Summary: Convert a whole brain T score map to a Z score map without loss of precision for strongly positive and negative values.
Home-page: https://github.com/vsoch/TtoZ
Author: UNKNOWN
Author-email: UNKNOWN
License: BSD
Keywords: nifti statistical brain maps
Platform: UNKNOWN
Classifier: Development Status :: 4 - Beta
Classifier: License :: OSI Approved :: BSD License
Classifier: Programming Language :: Python :: 2.6
Classifier: Programming Language :: Python :: 2.7
